source/buttons.py
source/config.py
source/database.py
source/main.py
krx_warehouse_tg-1.0.0.dist-info/METADATA
krx_warehouse_tg-1.0.0.dist-info/WHEEL
krx_warehouse_tg-1.0.0.dist-info/top_level.txt
krx_warehouse_tg-1.0.0.dist-info/RECORD
