Metadata-Version: 2.1
Name: krx_warehouse_tg
Version: 1.0.0
Summary: Telegram bot warehouse
Author: wkramx
Project-URL: Homepage, https://github.com/lrrrtm/krx_warehouse_bot
Classifier: Programming Language :: Python :: 3
Classifier: License :: OSI Approved :: MIT License
Classifier: Operating System :: OS Independent
Requires-Python: >=3.8
